pypokeclient/__init__.py
pypokeclient/async_client.py
pypokeclient/base_client.py
pypokeclient/sprite.py
pypokeclient/sync_client.py
pypokeclient/_api/__init__.py
pypokeclient/_api/common_models.py
pypokeclient/_api/languages.py
pypokeclient/_api/resource_lists.py
pypokeclient/_api/berries/__init__.py
pypokeclient/_api/berries/berries.py
pypokeclient/_api/berries/berry_firmnesses.py
pypokeclient/_api/berries/berry_flavors.py
pypokeclient/_api/contests/__init__.py
pypokeclient/_api/contests/contest_effects.py
pypokeclient/_api/contests/contest_types.py
pypokeclient/_api/contests/super_contest_effects.py
pypokeclient/_api/encounters/__init__.py
pypokeclient/_api/encounters/encounter_condition_values.py
pypokeclient/_api/encounters/encounter_conditions.py
pypokeclient/_api/encounters/encounter_methods.py
pypokeclient/_api/evolution/__init__.py
pypokeclient/_api/evolution/evolution_chains.py
pypokeclient/_api/evolution/evolution_triggers.py
pypokeclient/_api/games/__init__.py
pypokeclient/_api/games/generations.py
pypokeclient/_api/games/pokedexes.py
pypokeclient/_api/games/version.py
pypokeclient/_api/games/version_groups.py
pypokeclient/_api/items/__init__.py
pypokeclient/_api/items/item_attributes.py
pypokeclient/_api/items/item_categories.py
pypokeclient/_api/items/item_fling_effects.py
pypokeclient/_api/items/item_pockets.py
pypokeclient/_api/items/items.py
pypokeclient/_api/locations/__init__.py
pypokeclient/_api/locations/location_areas.py
pypokeclient/_api/locations/locations.py
pypokeclient/_api/locations/pal_park_areas.py
pypokeclient/_api/locations/regions.py
pypokeclient/_api/machines/__init__.py
pypokeclient/_api/machines/machines.py
pypokeclient/_api/moves/__init__.py
pypokeclient/_api/moves/move_ailments.py
pypokeclient/_api/moves/move_battle_styles.py
pypokeclient/_api/moves/move_categories.py
pypokeclient/_api/moves/move_damage_classes.py
pypokeclient/_api/moves/move_learn_methods.py
pypokeclient/_api/moves/move_targets.py
pypokeclient-1.1.0.dist-info/METADATA
pypokeclient-1.1.0.dist-info/WHEEL
pypokeclient-1.1.0.dist-info/licenses/LICENSE
pypokeclient-1.1.0.dist-info/RECORD
