Metadata-Version: 2.4
Name: pypokeclient
Version: 1.1.0
Summary: Synchronous and asynchronous clients to interact with PokéAPI
Project-URL: Homepage, https://github.com/RistoAle97/pokeapi-python-wrapper
Project-URL: Documentation, https://ristoale97.github.io/pokeapi-python-wrapper/
Project-URL: Repository, https://github.com/RistoAle97/pokeapi-python-wrapper
Project-URL: Issues, https://github.com/RistoAle97/pokeapi-python-wrapper/issues
Author-email: Alessandro Ristori <aleristori97@gmail.com>
License: MIT License
License-File: LICENSE
Keywords: pokeapi,pokemon-api
Classifier: Development Status :: 5 - Production/Stable
Classifier: License :: OSI Approved :: MIT License
Classifier: Programming Language :: Python :: 3 :: Only
Classifier: Programming Language :: Python :: 3.12
Classifier: Programming Language :: Python :: 3.13
Classifier: Programming Language :: Python :: 3.14
Requires-Python: >=3.12
Requires-Dist: aiohttp-client-cache[all]>=0.13.0
Requires-Dist: aiohttp>=3.12.15
Requires-Dist: pydantic>=2.11.7
Requires-Dist: requests-cache>=1.2.1
Requires-Dist: requests>=2.32.4
